aiorchestra_openstack_plugin-0.1.3.dist-info/DESCRIPTION.rst
aiorchestra_openstack_plugin-0.1.3.dist-info/METADATA
aiorchestra_openstack_plugin-0.1.3.dist-info/RECORD
aiorchestra_openstack_plugin-0.1.3.dist-info/WHEEL
aiorchestra_openstack_plugin-0.1.3.dist-info/metadata.json
aiorchestra_openstack_plugin-0.1.3.dist-info/top_level.txt
aiorchestra_openstack_plugin-0.1.3.dist-info/zip-safe
openstack_plugin/__init__.py
openstack_plugin/access_and_security/__init__.py
openstack_plugin/access_and_security/authorization.py
openstack_plugin/access_and_security/ssh.py
openstack_plugin/common/__init__.py
openstack_plugin/common/clients.py
openstack_plugin/compute/__init__.py
openstack_plugin/compute/instances.py
openstack_plugin/networking/__init__.py
openstack_plugin/networking/floating_ip.py
openstack_plugin/networking/network.py
openstack_plugin/networking/port.py
openstack_plugin/networking/router.py
openstack_plugin/networking/security_group_and_rules.py
openstack_plugin/networking/subnet.py
openstack_plugin/orchestration/__init__.py
openstack_plugin/orchestration/compute.py
openstack_plugin/orchestration/network.py
openstack_plugin/orchestration/stacks.py
openstack_plugin/tasks/__init__.py
openstack_plugin/tasks/authorization.py
openstack_plugin/tasks/compute.py
openstack_plugin/tasks/floating_ip.py
openstack_plugin/tasks/lbaas.py
openstack_plugin/tasks/net.py
openstack_plugin/tasks/port.py
openstack_plugin/tasks/router.py
openstack_plugin/tasks/security_group.py
openstack_plugin/tasks/ssh.py
openstack_plugin/tasks/subnet.py
openstack_plugin/tests/integration/__init__.py
openstack_plugin/tests/integration/base.py
openstack_plugin/tests/integration/config.py
openstack_plugin/tests/integration/test_auth.py
openstack_plugin/tests/integration/test_complex.py
openstack_plugin/tests/integration/test_compute.py
openstack_plugin/tests/integration/test_example_templates.py
openstack_plugin/tests/integration/test_networking.py
openstack_plugin/tests/integration/test_software_configuration.py
