Metadata-Version: 2.0
Name: aiorchestra-openstack-plugin
Version: 0.1.3
Summary: AsyncIO TOSCA orchestrator OpenStack plugin
Home-page: https://aiorchestra.io/
Author: Denys Makogon
Author-email: lildee1991@gmail.com
License: License :: OSI Approved :: Apache Software License
Keywords: orchestration,python,framework,asyncio,uvloop,OpenStack,OpenStack Heat
Platform: Linux
Platform: Mac OS-X
Platform: Unix
Classifier: License :: OSI Approved :: Apache Software License
Classifier: Intended Audience :: Information Technology
Classifier: Intended Audience :: System Administrators
Classifier: Intended Audience :: Developers
Classifier: Environment :: No Input/Output (Daemon)
Classifier: Programming Language :: Python :: 2.7
Classifier: Programming Language :: Python :: 3.4
Classifier: Programming Language :: Python :: 3.5
Classifier: Topic :: Software Development :: Libraries :: Python Modules
Classifier: Topic :: System :: Distributed Computing
Classifier: Operating System :: Microsoft :: Windows
Classifier: Operating System :: POSIX
Classifier: Operating System :: Unix
Classifier: Operating System :: MacOS
Requires-Dist: aiorchestra (==0.1.3)
Requires-Dist: python-glanceclient
Requires-Dist: python-heatclient
Requires-Dist: python-neutronclient
Requires-Dist: python-novaclient
